[
    {
        "date": "2000-08-13T00:00:00.000Z",
        "fromId": 96,
        "fromEmail": "matthew.lenhart@enron.com",
        "fromJobtitle": "Employee",
        "toId": 77,
        "toEmail": "eric.bass@enron.com",
        "toJobtitle": "Trader",
        "messageType": "CC",
        "sentiment": 0.0136986301369863
    },
    {
        "date": "2000-08-13T00:00:00.000Z",
        "fromId": 96,
        "fromEmail": "matthew.lenhart@enron.com",
        "fromJobtitle": "Employee",
        "toId": 77,
        "toEmail": "eric.bass@enron.com",
        "toJobtitle": "Trader",
        "messageType": "CC",
        "sentiment": 0.0136986301369863
    },
    {
        "date": "2000-08-13T00:00:00.000Z",
        "fromId": 96,
        "fromEmail": "matthew.lenhart@enron.com",
        "fromJobtitle": "Employee",
        "toId": 112,
        "toEmail": "phillip.m.love@enron.com",
        "toJobtitle": "Unknown",
        "messageType": "TO",
        "sentiment": 0.0136986301369863
    },
    {
        "date": "2001-11-22T00:00:00.000Z",
        "fromId": 64,
        "fromEmail": "danny.mccarty@enron.com",
        "fromJobtitle": "Vice President",
        "toId": 121,
        "toEmail": "rod.hayslett@enron.com",
        "toJobtitle": "Vice President",
        "messageType": "TO",
        "sentiment": 0
    },
    {
        "date": "2000-10-29T00:00:00.000Z",
        "fromId": 139,
        "fromEmail": "susan.scott@enron.com",
        "fromJobtitle": "Unknown",
        "toId": 104,
        "toEmail": "monique.sanchez@enron.com",
        "toJobtitle": "Unknown",
        "messageType": "TO",
        "sentiment": 0
    },
    {
        "date": "2000-10-11T00:00:00.000Z",
        "fromId": 48,
        "fromEmail": "andy.zipper@enron.com",
        "fromJobtitle": "Vice President",
        "toId": 2,
        "toEmail": "mark.e.taylor@enron.com",
        "toJobtitle": "Employee",
        "messageType": "TO",
        "sentiment": 0.0273972602739726
    },
    {
        "date": "2001-09-25T00:00:00.000Z",
        "fromId": 69,
        "fromEmail": "debra.perlingiere@enron.com",
        "fromJobtitle": "Employee",
        "toId": 105,
        "toEmail": "patrice.l.mims@enron.com",
        "toJobtitle": "Unknown",
        "messageType": "TO",
        "sentiment": 0
    },
    {
        "date": "2000-07-27T00:00:00.000Z",
        "fromId": 148,
        "fromEmail": "j.kaminski@enron.com",
        "fromJobtitle": "Manager",
        "toId": 15,
        "toEmail": "kevin.m.presto@enron.com",
        "toJobtitle": "Vice President",
        "messageType": "TO",
        "sentiment": 0.0273972602739726
    },
    {
        "date": "2001-11-14T00:00:00.000Z",
        "fromId": 87,
        "fromEmail": "mark.whitt@enron.com",
        "fromJobtitle": "Unknown",
        "toId": 49,
        "toEmail": "barry.tycholiz@enron.com",
        "toJobtitle": "Vice President",
        "messageType": "TO",
        "sentiment": 0.0136986301369863
    },
    {
        "date": "2002-03-26T00:00:00.000Z",
        "fromId": 57,
        "fromEmail": "chris.germany@enron.com",
        "fromJobtitle": "Employee",
        "toId": 57,
        "toEmail": "chris.germany@enron.com",
        "toJobtitle": "Employee",
        "messageType": "TO",
        "sentiment": 0
    },
    {
        "date": "2000-08-20T00:00:00.000Z",
        "fromId": 87,
        "fromEmail": "mark.whitt@enron.com",
        "fromJobtitle": "Unknown",
        "toId": 84,
        "toEmail": "gerald.nemec@enron.com",
        "toJobtitle": "Unknown",
        "messageType": "TO",
        "sentiment": 0
    },
    {
        "date": "2001-04-08T00:00:00.000Z",
        "fromId": 62,
        "fromEmail": "dan.hyvl@enron.com",
        "fromJobtitle": "Employee",
        "toId": 131,
        "toEmail": "stacy.dickson@enron.com",
        "toJobtitle": "Employee",
        "messageType": "TO",
        "sentiment": 0
    },
    {
        "date": "2000-01-26T00:00:00.000Z",
        "fromId": 110,
        "fromEmail": "phillip.k.ellen@enron.com",
        "fromJobtitle": "Manager",
        "toId": 35,
        "toEmail": "hunter.s.shively@enron.com",
        "toJobtitle": "Vice President",
        "messageType": "TO",
        "sentiment": 0
    },
    {
        "date": "2000-01-26T00:00:00.000Z",
        "fromId": 110,
        "fromEmail": "phillip.k.ellen@enron.com",
        "fromJobtitle": "Manager",
        "toId": 80,
        "toEmail": "fletcher.j.sturm@enron.com",
        "toJobtitle": "Vice President",
        "messageType": "TO",
        "sentiment": 0
    },
    {
        "date": "2000-07-10T00:00:00.000Z",
        "fromId": 55,
        "fromEmail": "carol.clair@enron.com",
        "fromJobtitle": "Vice President",
        "toId": 140,
        "toEmail": "susan.bailey@enron.com",
        "toJobtitle": "Unknown",
        "messageType": "CC",
        "sentiment": 0.0136986301369863
    },
    {
        "date": "2001-11-04T00:00:00.000Z",
        "fromId": 17,
        "fromEmail": "kimberly.watson@enron.com",
        "fromJobtitle": "Unknown",
        "toId": 3,
        "toEmail": "lindy.donoho@enron.com",
        "toJobtitle": "Employee",
        "messageType": "CC",
        "sentiment": 0
    },
    {
        "date": "2001-06-02T00:00:00.000Z",
        "fromId": 75,
        "fromEmail": "elizabeth.sager@enron.com",
        "fromJobtitle": "Employee",
        "toId": 9,
        "toEmail": "kay.mann@enron.com",
        "toJobtitle": "Employee",
        "messageType": "CC",
        "sentiment": 0.0136986301369863
    },
    {
        "date": "2001-11-04T00:00:00.000Z",
        "fromId": 17,
        "fromEmail": "kimberly.watson@enron.com",
        "fromJobtitle": "Unknown",
        "toId": 107,
        "toEmail": "paul.y barbo@enron.com",
        "toJobtitle": "Trader",
        "messageType": "CC",
        "sentiment": 0
    }
]
